LICENSE.txt
README.md
setup.cfg
setup.py
pysyncobj/__init__.py
pysyncobj/atomic_replace.py
pysyncobj/batteries.py
pysyncobj/config.py
pysyncobj/dns_resolver.py
pysyncobj/encryptor.py
pysyncobj/fast_queue.py
pysyncobj/journal.py
pysyncobj/monotonic.py
pysyncobj/node.py
pysyncobj/pickle.py
pysyncobj/pipe_notifier.py
pysyncobj/poller.py
pysyncobj/serializer.py
pysyncobj/syncobj.py
pysyncobj/syncobj_admin.py
pysyncobj/tcp_connection.py
pysyncobj/tcp_server.py
pysyncobj/transport.py
pysyncobj/utility.py
pysyncobj/version.py
pysyncobj/win_inet_pton.py
pysyncobj.egg-info/PKG-INFO
pysyncobj.egg-info/SOURCES.txt
pysyncobj.egg-info/dependency_links.txt
pysyncobj.egg-info/entry_points.txt
pysyncobj.egg-info/top_level.txt