Metadata-Version: 2.1
Name: pysyncobj
Version: 0.3.11
Summary: A library for replicating your python class between multiple servers, based on raft protocol
Home-page: https://github.com/bakwc/PySyncObj
Download-URL: https://github.com/bakwc/PySyncObj/tarball/0.3.11
Author: Filipp Ozinov
Author-email: fippo@mail.ru
License: MIT
Keywords: network,replication,raft,synchronization
Platform: UNKNOWN
Classifier: Topic :: System :: Networking
Classifier: Topic :: System :: Distributed Computing
Classifier: Intended Audience :: Developers
Classifier: Programming Language :: Python :: 2.7
Classifier: Programming Language :: Python :: 3.4
Classifier: Programming Language :: Python :: 3.5
Classifier: Operating System :: POSIX :: Linux
Classifier: Operating System :: MacOS :: MacOS X
Classifier: License :: OSI Approved :: MIT License
License-File: LICENSE.txt
